{
  "gate": "plan",
  "project": "experiments/strategic-niche-audit",
  "timestamp": "2026-06-26T05:13:44.666584+00:00",
  "verdicts": [
    {
      "angle": "bugs",
      "verdict": "APPROVE",
      "severity": "low",
      "reason": "The plan thoroughly addresses potential correctness issues, explicitly stating data provenance, enforcing advisory-only boundaries, and including robust verification steps for data integrity within the audit document.",
      "required_fix": "",
      "evidence": "",
      "veto": false,
      "parse_failed": false
    },
    {
      "angle": "security",
      "verdict": "APPROVE",
      "severity": "low",
      "reason": "The plan explicitly states no code execution, no secrets read, no network calls, and no modification of critical system state, effectively eliminating common attack surfaces.",
      "required_fix": "",
      "evidence": "",
      "veto": false,
      "parse_failed": false
    },
    {
      "angle": "ui",
      "verdict": "APPROVE",
      "severity": "low",
      "reason": "The deliverable is a documentation artifact (a markdown file) and does not involve any user interface elements or interactions to evaluate.",
      "required_fix": "",
      "evidence": "UI: N/A \u2014 documentation artifact, no UI.",
      "veto": false,
      "parse_failed": false
    },
    {
      "angle": "guide",
      "verdict": "APPROVE",
      "severity": "low",
      "reason": "The plan explicitly details the structure, content, and provenance of the deliverable, ensuring high discoverability for both human and AI readers.",
      "required_fix": "",
      "evidence": "",
      "veto": false,
      "parse_failed": false
    },
    {
      "angle": "usefulness",
      "verdict": "APPROVE",
      "severity": "low",
      "reason": "The audit provides a clear strategic tool for the portfolio owner to assess defensibility and guide future development, addressing a real need for strategic alignment.",
      "required_fix": "",
      "evidence": "The 'human architect/owner' is a clear second user, and the problem of 'undifferentiated tooling' is a common strategic concern in product development.",
      "veto": false,
      "parse_failed": false
    },
    {
      "angle": "cool",
      "verdict": "APPROVE",
      "severity": "",
      "reason": "The audit document's signature move is its specific, actionable flagging of existing portfolio items by slug against a reconstructed strategic framework, providing concrete targets for review for the human architect.",
      "required_fix": "",
      "evidence": "",
      "veto": false,
      "parse_failed": false
    },
    {
      "angle": "lessons",
      "verdict": "APPROVE",
      "severity": "low",
      "reason": "",
      "required_fix": "",
      "evidence": "",
      "veto": false,
      "parse_failed": false
    }
  ],
  "all_approved": true,
  "objections": [],
  "vetoed": false
}